[
  {
    "id": "01",
    "title": "Desafio 01",
    "description": "Fazer um programa para calcular a média de 3 números."
  },
  {
    "id": "02",
    "title": "Desafio 02",
    "description": "Fazer um programa para verificar se um número é primo."
  },
  {
    "id": "01",
    "title": "Triângulo",
    "description": "Fazer um programa para calcular a média de 3 números."
  },
  {
    "id": "02",
    "title": "Desafio 02",
    "description": "Fazer um programa para verificar se um número é primo."
  },
  {
    "id": "01",
    "title": "Desafio 01",
    "description": "Fazer um programa para calcular a média de 3 números.Fazer um programa para calcular a média de 3 números.Fazer um programa para calcular a média de 3 números."
  },
  {
    "id": "02",
    "title": "Desafio 02",
    "description": "Fazer um programa para verificar se um número é primo."
  },
  {
    "id": "01",
    "title": "Desafio 01",
    "description": "Fazer um programa para calcular a média de 3 números."
  },
  {
    "id": "02",
    "title": "Desafio 02",
    "description": "Fazer um programa para verificar se um número é primo."
  },
  {
    "id": "01",
    "title": "Desafio 01",
    "description": "Fazer um programa para calcular a média de 3 números."
  },
  {
    "id": "02",
    "title": "Desafio 02",
    "description": "Fazer um programa para verificar se um número é primo."
  },
  {
    "id": "01",
    "title": "Desafio 01",
    "description": "Fazer um programa para calcular a média de 3 números."
  },
  {
    "id": "03",
    "title": "Desafio 03",
    "description": "Fazer um programa para contar quantas vogais tem uma frase."
  }
]